cognite/examples/unstable/extractors/simple_extractor/main.py
cognite/examples/unstable/extractors/simple_extractor/config/config.yaml
cognite/examples/unstable/extractors/simple_extractor/config/connection_config.yaml
cognite/extractorutils/__init__.py
cognite/extractorutils/_inner_util.py
cognite/extractorutils/base.py
cognite/extractorutils/exceptions.py
cognite/extractorutils/metrics.py
cognite/extractorutils/py.typed
cognite/extractorutils/threading.py
cognite/extractorutils/uploader_extractor.py
cognite/extractorutils/uploader_types.py
cognite/extractorutils/util.py
cognite/extractorutils/configtools/__init__.py
cognite/extractorutils/configtools/_util.py
cognite/extractorutils/configtools/elements.py
cognite/extractorutils/configtools/loaders.py
cognite/extractorutils/configtools/validators.py
cognite/extractorutils/statestore/__init__.py
cognite/extractorutils/statestore/_base.py
cognite/extractorutils/statestore/hashing.py
cognite/extractorutils/statestore/watermark.py
cognite/extractorutils/unstable/__init__.py
cognite/extractorutils/unstable/configuration/__init__.py
cognite/extractorutils/unstable/configuration/exceptions.py
cognite/extractorutils/unstable/configuration/loaders.py
cognite/extractorutils/unstable/configuration/models.py
cognite/extractorutils/unstable/core/__init__.py
cognite/extractorutils/unstable/core/_dto.py
cognite/extractorutils/unstable/core/_messaging.py
cognite/extractorutils/unstable/core/base.py
cognite/extractorutils/unstable/core/checkin_worker.py
cognite/extractorutils/unstable/core/errors.py
cognite/extractorutils/unstable/core/logger.py
cognite/extractorutils/unstable/core/restart_policy.py
cognite/extractorutils/unstable/core/runtime.py
cognite/extractorutils/unstable/core/tasks.py
cognite/extractorutils/unstable/scheduling/__init__.py
cognite/extractorutils/unstable/scheduling/_scheduler.py
cognite/extractorutils/unstable/scheduling/_schedules.py
cognite/extractorutils/uploader/__init__.py
cognite_extractor_utils-7.11.3.dist-info/METADATA
cognite_extractor_utils-7.11.3.dist-info/WHEEL
cognite_extractor_utils-7.11.3.dist-info/entry_points.txt
cognite_extractor_utils-7.11.3.dist-info/licenses/LICENSE
cognite_extractor_utils-7.11.3.dist-info/RECORD
