Metadata-Version: 2.4
Name: cognite-extractor-utils
Version: 7.11.3
Summary: Utilities for easier development of extractors for CDF
Project-URL: repository, https://github.com/cognitedata/python-extractor-utils
Author-email: Mathias Lohne <mathias.lohne@cognite.com>
License: Apache-2.0
License-File: LICENSE
Classifier: Development Status :: 5 - Production/Stable
Classifier: Programming Language :: Python
Requires-Python: >=3.10
Requires-Dist: arrow>=1.0.0
Requires-Dist: azure-identity>=1.14.0
Requires-Dist: azure-keyvault-secrets>=4.7.0
Requires-Dist: cognite-sdk>=7.90.0
Requires-Dist: croniter>=6.0.0
Requires-Dist: dacite<1.10.0,>=1.9.2
Requires-Dist: decorator>=5.1.1
Requires-Dist: httpx<1,>=0.27.0
Requires-Dist: jsonlines>=4.0.0
Requires-Dist: more-itertools>=10.0.0
Requires-Dist: orjson>=3.10.3
Requires-Dist: prometheus-client<=1.0.0,>=0.7.0
Requires-Dist: psutil>=6.0.0
Requires-Dist: pydantic>=2.8.2
Requires-Dist: pyhumps>=3.8.0
Requires-Dist: python-dotenv>=1.0.0
Requires-Dist: pyyaml<7,>=5.3.0
Requires-Dist: simple-winservice>=0.1.0; sys_platform == 'win32'
Requires-Dist: typing-extensions<5,>=3.7.4
Provides-Extra: experimental
Requires-Dist: cognite-sdk-experimental; extra == 'experimental'
